newhello.py
newnewhello.py
newhello-0.0.5.dist-info/METADATA
newhello-0.0.5.dist-info/WHEEL
newhello-0.0.5.dist-info/top_level.txt
newhello-0.0.5.dist-info/RECORD
