Metadata-Version: 2.1
Name: newhello
Version: 0.0.5
Summary: Say hello!
Home-page: UNKNOWN
Author: UNKNOWN
Author-email: UNKNOWN
License: UNKNOWN
Platform: UNKNOWN
